fivetran_customer_sdk/__init__.py
fivetran_customer_sdk/protos/__init__.py
fivetran_customer_sdk/protos/common_pb2.py
fivetran_customer_sdk/protos/common_pb2.pyi
fivetran_customer_sdk/protos/common_pb2_grpc.py
fivetran_customer_sdk/protos/connector_sdk_pb2.py
fivetran_customer_sdk/protos/connector_sdk_pb2.pyi
fivetran_customer_sdk/protos/connector_sdk_pb2_grpc.py
fivetran_customer_sdk-0.4.8.1.dist-info/LICENSE
fivetran_customer_sdk-0.4.8.1.dist-info/METADATA
fivetran_customer_sdk-0.4.8.1.dist-info/WHEEL
fivetran_customer_sdk-0.4.8.1.dist-info/entry_points.txt
fivetran_customer_sdk-0.4.8.1.dist-info/top_level.txt
fivetran_customer_sdk-0.4.8.1.dist-info/RECORD
