Metadata-Version: 2.1
Name: fivetran_customer_sdk
Version: 0.4.8.1
Summary: Build custom connectors on Fivetran platform
Author-email: Fivetran <developers@fivetran.com>
Project-URL: Homepage, https://fivetran.com/docs/my-built-connector
Project-URL: Github, https://github.com/fivetran/fivetran_customer_sdk
Classifier: Programming Language :: Python :: 3
Classifier: License :: OSI Approved :: MIT License
Classifier: Operating System :: OS Independent
Requires-Python: >=3.9
License-File: LICENSE
Requires-Dist: grpcio ==1.59.3
Requires-Dist: grpcio-tools ==1.59.3
Requires-Dist: docker ==6.1.3
Requires-Dist: requests ==2.31.0
